{
  "questions": [
    {
      "question": "Which is the most popular JavaScript framework?",
      "options": ["Angular", "React", "Svelte", "Vue"],
      "correctOption": 1,
      "points": 10
    },
    {
      "question": "Which company invented React?",
      "options": ["Google", "Apple", "Netflix", "Facebook"],
      "correctOption": 3,
      "points": 10
    },
    {
      "question": "What does 'undefined' represent in JavaScript? ",
      "options": [
        "A variable that has not been declared",
        "A variable with no assigned value",
        "An error in the code",
        "An empty array or object"
      ],
      "correctOption": 1,
      "points": 10
    }
  ]
}
